{
  "Items": [
    {
      "date": {
        "N": "1507330668611"
      },
      "branchid": {
        "S": "root"
      },
      "wrong_type_count": {
        "N": "1"
      },
      "nsfw_count": {
        "N": "0"
      },
      "id": {
        "S": "lmenus-1507330656783"
      },
      "type": {
        "S": "text"
      },
      "branch_rules_count": {
        "N": "0"
      },
      "site_rules_count": {
        "N": "0"
      }
    },
    {
      "date": {
        "N": "1515399686839"
      },
      "branchid": {
        "S": "root"
      },
      "wrong_type_count": {
        "N": "0"
      },
      "nsfw_count": {
        "N": "0"
      },
      "id": {
        "S": "james-1507578405572"
      },
      "type": {
        "S": "text"
      },
      "branch_rules_count": {
        "N": "1"
      },
      "site_rules_count": {
        "N": "0"
      }
    },
    {
      "date": {
        "N": "1515399696938"
      },
      "branchid": {
        "S": "root"
      },
      "wrong_type_count": {
        "N": "0"
      },
      "nsfw_count": {
        "N": "1"
      },
      "id": {
        "S": "hyphen-name-1514668732645"
      },
      "type": {
        "S": "text"
      },
      "branch_rules_count": {
        "N": "0"
      },
      "site_rules_count": {
        "N": "0"
      }
    },
    {
      "date": {
        "N": "1558111406931"
      },
      "branchid": {
        "S": "root"
      },
      "wrong_type_count": {
        "N": "0"
      },
      "nsfw_count": {
        "N": "0"
      },
      "id": {
        "S": "james-1498145844309"
      },
      "type": {
        "S": "video"
      },
      "branch_rules_count": {
        "N": "1"
      },
      "site_rules_count": {
        "N": "0"
      }
    },
    {
      "date": {
        "N": "1515098772370"
      },
      "branchid": {
        "S": "root"
      },
      "wrong_type_count": {
        "N": "0"
      },
      "nsfw_count": {
        "N": "0"
      },
      "id": {
        "S": "lmenus-1514668435068"
      },
      "type": {
        "S": "text"
      },
      "branch_rules_count": {
        "N": "1"
      },
      "site_rules_count": {
        "N": "0"
      }
    },
    {
      "date": {
        "N": "1504370663942"
      },
      "branchid": {
        "S": "root"
      },
      "wrong_type_count": {
        "N": "2"
      },
      "nsfw_count": {
        "N": "0"
      },
      "id": {
        "S": "lmenus-1504370547320"
      },
      "type": {
        "S": "text"
      },
      "branch_rules_count": {
        "N": "0"
      },
      "site_rules_count": {
        "N": "0"
      }
    }
  ],
  "Count": 6,
  "ScannedCount": 6
}